{
  "dataset_revision": null,
  "mteb_dataset_name": "FewRelClustering",
  "mteb_version": "1.1.2.dev0",
  "test": {
    "cluster_components": [
      [
        {
          "country of citizenship": 9,
          "father": 1,
          "field of work": 10,
          "genre": 1,
          "instrument": 15,
          "member of political party": 1,
          "military branch": 2,
          "movement": 1,
          "occupation": 34,
          "religion": 3,
          "residence": 3,
          "sibling": 2,
          "work location": 5
        },
        {
          "after a work by": 12,
          "architect": 3,
          "characters": 1,
          "composer": 1,
          "country": 3,
          "country of citizenship": 5,
          "country of origin": 2,
          "field of work": 18,
          "genre": 3,
          "headquarters location": 1,
          "instrument": 1,
          "military branch": 1,
          "movement": 10,
          "notable work": 21,
          "occupant": 1,
          "occupation": 3,
          "operator": 1,
          "religion": 5,
          "residence": 6,
          "screenwriter": 4,
          "subsidiary": 1,
          "winner": 1,
          "work location": 8
        },
        {
          "after a work by": 1,
          "characters": 4,
          "composer": 1,
          "country": 1,
          "country of citizenship": 3,
          "distributor": 1,
          "field of work": 2,
          "headquarters location": 1,
          "location": 1,
          "location of formation": 2,
          "manufacturer": 1,
          "member of political party": 2,
          "military branch": 2,
          "movement": 3,
          "notable work": 4,
          "operator": 1,
          "participant of": 1,
          "position held": 1,
          "religion": 2,
          "residence": 5,
          "screenwriter": 1,
          "winner": 1,
          "work location": 2
        },
        {
          "developer": 1,
          "field of work": 17,
          "instrument": 1,
          "location of formation": 1,
          "occupation": 1
        },
        {
          "characters": 3,
          "country": 1,
          "country of citizenship": 7,
          "father": 5,
          "field of work": 4,
          "has part": 1,
          "head of government": 10,
          "instance of": 1,
          "instrument": 1,
          "located in the administrative territorial entity": 1,
          "located on terrain feature": 1,
          "member of political party": 11,
          "military branch": 2,
          "movement": 7,
          "notable work": 1,
          "occupation": 2,
          "operator": 1,
          "position held": 17,
          "record label": 1,
          "religion": 8,
          "residence": 10,
          "said to be the same as": 2,
          "screenwriter": 1,
          "sibling": 7,
          "work location": 15
        },
        {
          "applies to jurisdiction": 2,
          "architect": 2,
          "developer": 18,
          "distributor": 6,
          "field of work": 1,
          "followed by": 1,
          "instance of": 4,
          "language of work or name": 1,
          "location of formation": 3,
          "manufacturer": 3,
          "occupant": 1,
          "operating system": 6,
          "operator": 1,
          "original network": 2,
          "owned by": 7,
          "performer": 1,
          "publisher": 15,
          "record label": 10,
          "subsidiary": 3
        },
        {
          "after a work by": 2,
          "applies to jurisdiction": 1,
          "architect": 1,
          "contains administrative territorial entity": 1,
          "country of citizenship": 1,
          "director": 2,
          "father": 1,
          "field of work": 2,
          "head of government": 5,
          "headquarters location": 2,
          "instrument": 3,
          "league": 1,
          "location": 1,
          "location of formation": 2,
          "manufacturer": 1,
          "member of political party": 1,
          "military branch": 3,
          "movement": 2,
          "notable work": 1,
          "occupation": 2,
          "performer": 1,
          "position held": 4,
          "religion": 4,
          "residence": 10,
          "screenwriter": 1,
          "sibling": 2,
          "subsidiary": 3,
          "work location": 10
        },
        {
          "applies to jurisdiction": 9,
          "contains administrative territorial entity": 1,
          "country": 2,
          "country of citizenship": 1,
          "field of work": 1,
          "head of government": 13,
          "instance of": 1,
          "located in the administrative territorial entity": 1,
          "member of political party": 10,
          "military branch": 1,
          "participant of": 1,
          "position held": 14,
          "religion": 1,
          "subsidiary": 1,
          "successful candidate": 9,
          "work location": 1
        },
        {
          "country of citizenship": 1,
          "father": 4,
          "field of work": 1,
          "member of political party": 1,
          "military branch": 2,
          "nominated for": 4,
          "occupation": 1,
          "participant of": 5,
          "performer": 1,
          "sibling": 1,
          "winner": 1
        },
        {
          "applies to jurisdiction": 14,
          "contains administrative territorial entity": 9,
          "country": 9,
          "country of origin": 7,
          "distributor": 1,
          "field of work": 2,
          "followed by": 2,
          "genre": 1,
          "has part": 4,
          "head of government": 3,
          "headquarters location": 11,
          "instance of": 1,
          "language of work or name": 2,
          "located in the administrative territorial entity": 6,
          "located on terrain feature": 3,
          "location": 4,
          "location of formation": 8,
          "manufacturer": 1,
          "military branch": 3,
          "notable work": 2,
          "operator": 6,
          "owned by": 2,
          "participant": 1,
          "participant of": 1,
          "place served by transport hub": 3,
          "religion": 2,
          "residence": 4,
          "subsidiary": 3,
          "winner": 1,
          "work location": 4
        },
        {
          "after a work by": 11,
          "applies to jurisdiction": 1,
          "architect": 1,
          "characters": 8,
          "composer": 5,
          "country of citizenship": 1,
          "country of origin": 2,
          "developer": 1,
          "field of work": 3,
          "followed by": 1,
          "has part": 2,
          "instance of": 2,
          "instrument": 1,
          "language of work or name": 1,
          "location of formation": 1,
          "movement": 2,
          "notable work": 13,
          "publisher": 2,
          "religion": 5,
          "said to be the same as": 2,
          "screenwriter": 6,
          "sibling": 1
        },
        {
          "applies to jurisdiction": 1,
          "father": 38,
          "field of work": 2,
          "has part": 1,
          "head of government": 2,
          "instance of": 1,
          "instrument": 1,
          "member of political party": 1,
          "military branch": 2,
          "position held": 3,
          "religion": 1,
          "residence": 4,
          "said to be the same as": 1,
          "sibling": 44,
          "winner": 1,
          "work location": 7
        },
        {
          "field of work": 1,
          "has part": 1,
          "instance of": 1,
          "manufacturer": 1,
          "operating system": 28,
          "platform": 4
        },
        {
          "applies to jurisdiction": 14,
          "characters": 1,
          "country": 4,
          "country of citizenship": 4,
          "country of origin": 3,
          "field of work": 1,
          "head of government": 22,
          "headquarters location": 6,
          "instance of": 1,
          "located in the administrative territorial entity": 1,
          "manufacturer": 1,
          "member of political party": 10,
          "military branch": 4,
          "occupant": 1,
          "operator": 1,
          "position held": 6,
          "religion": 1,
          "residence": 2,
          "successful candidate": 2,
          "work location": 3
        },
        {
          "after a work by": 5,
          "applies to jurisdiction": 1,
          "characters": 1,
          "country of citizenship": 1,
          "country of origin": 2,
          "developer": 2,
          "director": 1,
          "field of work": 2,
          "instance of": 3,
          "language of work or name": 21,
          "located on terrain feature": 1,
          "notable work": 3,
          "participant": 1,
          "participating team": 1,
          "publisher": 1,
          "said to be the same as": 1,
          "screenwriter": 3
        },
        {
          "country of citizenship": 2,
          "country of origin": 9,
          "director": 1,
          "field of work": 1,
          "genre": 21,
          "has part": 1,
          "headquarters location": 1,
          "instance of": 1,
          "instrument": 1,
          "language of work or name": 1,
          "location of formation": 9,
          "movement": 1,
          "notable work": 2,
          "performer": 10,
          "platform": 1,
          "record label": 9,
          "screenwriter": 1
        },
        {
          "characters": 1,
          "director": 1,
          "distributor": 2,
          "field of work": 2,
          "head of government": 6,
          "headquarters location": 1,
          "instance of": 1,
          "language of work or name": 1,
          "member of political party": 4,
          "movement": 1,
          "nominated for": 3,
          "notable work": 1,
          "occupation": 3,
          "original network": 1,
          "participant of": 1,
          "place served by transport hub": 1,
          "position held": 4,
          "record label": 1,
          "religion": 2,
          "residence": 1,
          "screenwriter": 1,
          "work location": 2
        },
        {
          "after a work by": 1,
          "architect": 1,
          "characters": 4,
          "composer": 1,
          "country": 1,
          "country of origin": 1,
          "field of work": 2,
          "followed by": 1,
          "headquarters location": 1,
          "instance of": 1,
          "language of work or name": 28,
          "movement": 1,
          "notable work": 3,
          "operator": 1,
          "performer": 2,
          "publisher": 4,
          "religion": 1,
          "residence": 1,
          "said to be the same as": 1
        },
        {
          "composer": 3,
          "country": 1,
          "country of origin": 1,
          "field of work": 3,
          "followed by": 6,
          "genre": 2,
          "has part": 3,
          "instance of": 4,
          "language of work or name": 1,
          "location": 2,
          "location of formation": 1,
          "movement": 5,
          "nominated for": 1,
          "notable work": 1,
          "operating system": 1,
          "performer": 1,
          "publisher": 1,
          "religion": 2,
          "said to be the same as": 9
        },
        {
          "architect": 1,
          "country": 2,
          "country of citizenship": 6,
          "country of origin": 1,
          "father": 1,
          "field of work": 1,
          "genre": 1,
          "instrument": 4,
          "located in the administrative territorial entity": 1,
          "member of political party": 2,
          "military branch": 26,
          "movement": 8,
          "occupation": 1,
          "participant of": 1,
          "position held": 1,
          "record label": 1,
          "religion": 5,
          "residence": 3,
          "said to be the same as": 1,
          "work location": 3
        },
        {
          "contains administrative territorial entity": 1,
          "country of citizenship": 12,
          "country of origin": 1,
          "field of work": 1,
          "genre": 2,
          "instance of": 1,
          "instrument": 2,
          "league": 1,
          "located in the administrative territorial entity": 2,
          "member of political party": 3,
          "nominated for": 1,
          "occupant": 1,
          "occupation": 1,
          "participant of": 36,
          "participating team": 1,
          "residence": 3,
          "successful candidate": 1,
          "work location": 1
        },
        {
          "after a work by": 5,
          "characters": 14,
          "composer": 6,
          "country of origin": 3,
          "developer": 1,
          "director": 1,
          "distributor": 2,
          "father": 1,
          "field of work": 1,
          "genre": 1,
          "has part": 7,
          "head of government": 1,
          "instance of": 2,
          "instrument": 13,
          "location of formation": 2,
          "manufacturer": 2,
          "military branch": 2,
          "movement": 2,
          "notable work": 6,
          "original network": 1,
          "participant of": 1,
          "performer": 5,
          "position held": 1,
          "record label": 4,
          "religion": 2,
          "residence": 1,
          "said to be the same as": 1,
          "screenwriter": 8,
          "sibling": 1,
          "winner": 2,
          "work location": 4
        },
        {
          "after a work by": 1,
          "applies to jurisdiction": 2,
          "architect": 33,
          "characters": 1,
          "composer": 4,
          "country": 4,
          "country of citizenship": 1,
          "country of origin": 2,
          "director": 2,
          "field of work": 2,
          "genre": 5,
          "has part": 1,
          "head of government": 1,
          "heritage designation": 2,
          "instrument": 4,
          "league": 1,
          "licensed to broadcast to": 1,
          "located in the administrative territorial entity": 3,
          "located on terrain feature": 2,
          "location": 3,
          "location of formation": 3,
          "manufacturer": 3,
          "mountain range": 1,
          "movement": 15,
          "notable work": 3,
          "occupation": 2,
          "operating system": 1,
          "operator": 1,
          "owned by": 1,
          "place served by transport hub": 1,
          "publisher": 1,
          "religion": 3,
          "said to be the same as": 1,
          "work location": 1
        },
        {
          "after a work by": 3,
          "characters": 8,
          "composer": 9,
          "contains administrative territorial entity": 1,
          "country of origin": 2,
          "developer": 7,
          "director": 6,
          "distributor": 10,
          "followed by": 6,
          "genre": 6,
          "has part": 3,
          "instance of": 2,
          "language of work or name": 4,
          "league": 1,
          "located on terrain feature": 1,
          "location of formation": 1,
          "nominated for": 1,
          "notable work": 2,
          "operator": 3,
          "original network": 15,
          "owned by": 1,
          "participant": 1,
          "performer": 17,
          "place served by transport hub": 1,
          "platform": 2,
          "publisher": 7,
          "record label": 8,
          "residence": 1,
          "said to be the same as": 2,
          "screenwriter": 4
        },
        {
          "after a work by": 1,
          "composer": 1,
          "country of citizenship": 2,
          "country of origin": 3,
          "developer": 2,
          "distributor": 4,
          "genre": 3,
          "has part": 6,
          "headquarters location": 2,
          "instrument": 3,
          "location of formation": 11,
          "movement": 1,
          "nominated for": 4,
          "notable work": 3,
          "original network": 5,
          "participant of": 1,
          "performer": 2,
          "record label": 12,
          "residence": 3,
          "screenwriter": 3,
          "winner": 2
        },
        {
          "after a work by": 5,
          "characters": 1,
          "composer": 10,
          "country": 1,
          "country of origin": 4,
          "developer": 1,
          "director": 3,
          "distributor": 5,
          "followed by": 1,
          "genre": 5,
          "has part": 2,
          "headquarters location": 1,
          "instance of": 2,
          "language of work or name": 2,
          "location": 3,
          "operator": 1,
          "original network": 13,
          "participant": 1,
          "performer": 7,
          "publisher": 1,
          "record label": 3,
          "screenwriter": 3
        },
        {
          "characters": 1,
          "composer": 2,
          "country of origin": 1,
          "developer": 15,
          "director": 1,
          "distributor": 15,
          "genre": 8,
          "has part": 4,
          "instance of": 4,
          "location of formation": 2,
          "original network": 8,
          "performer": 2,
          "platform": 20,
          "publisher": 10,
          "record label": 12,
          "screenwriter": 2
        },
        {
          "has part": 2,
          "headquarters location": 2,
          "league": 4,
          "location of formation": 1,
          "operator": 1,
          "owned by": 4,
          "record label": 3,
          "screenwriter": 1,
          "subsidiary": 2
        },
        {
          "after a work by": 2,
          "characters": 1,
          "composer": 6,
          "country of citizenship": 1,
          "director": 9,
          "distributor": 4,
          "followed by": 1,
          "has part": 7,
          "instance of": 1,
          "instrument": 3,
          "location of formation": 5,
          "movement": 1,
          "nominated for": 1,
          "notable work": 3,
          "occupation": 1,
          "original network": 2,
          "participant": 1,
          "performer": 3,
          "publisher": 1,
          "record label": 4,
          "said to be the same as": 1,
          "screenwriter": 8,
          "sibling": 1,
          "winner": 1,
          "work location": 1
        },
        {
          "architect": 1,
          "characters": 2,
          "composer": 1,
          "developer": 9,
          "distributor": 2,
          "followed by": 3,
          "genre": 5,
          "instance of": 3,
          "located on terrain feature": 1,
          "location": 2,
          "location of formation": 1,
          "manufacturer": 8,
          "movement": 1,
          "operating system": 8,
          "operator": 1,
          "original network": 9,
          "performer": 1,
          "place served by transport hub": 1,
          "platform": 33,
          "publisher": 10,
          "record label": 4,
          "subsidiary": 1
        },
        {
          "country of origin": 1,
          "followed by": 2,
          "nominated for": 40,
          "performer": 1,
          "record label": 1,
          "screenwriter": 1,
          "sports season of league or competition": 1,
          "winner": 11
        },
        {
          "after a work by": 8,
          "applies to jurisdiction": 1,
          "architect": 2,
          "characters": 7,
          "composer": 6,
          "country": 1,
          "country of origin": 1,
          "director": 8,
          "distributor": 2,
          "followed by": 1,
          "genre": 1,
          "has part": 3,
          "headquarters location": 1,
          "instance of": 1,
          "instrument": 1,
          "licensed to broadcast to": 1,
          "location": 5,
          "location of formation": 2,
          "manufacturer": 5,
          "notable work": 4,
          "operator": 1,
          "original network": 4,
          "participant": 3,
          "participating team": 2,
          "performer": 6,
          "place served by transport hub": 1,
          "platform": 1,
          "publisher": 3,
          "record label": 2,
          "residence": 1,
          "screenwriter": 10,
          "winner": 1
        },
        {
          "applies to jurisdiction": 1,
          "country": 1,
          "country of origin": 1,
          "developer": 6,
          "followed by": 8,
          "headquarters location": 1,
          "instance of": 5,
          "manufacturer": 25,
          "operating system": 22,
          "operator": 10,
          "owned by": 1,
          "platform": 2,
          "subsidiary": 2,
          "work location": 1
        },
        {
          "applies to jurisdiction": 3,
          "country": 4,
          "country of origin": 1,
          "developer": 1,
          "followed by": 2,
          "genre": 1,
          "has part": 3,
          "head of government": 2,
          "headquarters location": 3,
          "league": 2,
          "licensed to broadcast to": 4,
          "location of formation": 1,
          "manufacturer": 3,
          "member of political party": 2,
          "military branch": 1,
          "occupant": 2,
          "operating system": 1,
          "operator": 1,
          "owned by": 21,
          "participant": 1,
          "publisher": 1,
          "religion": 2,
          "said to be the same as": 1,
          "subsidiary": 26
        },
        {
          "architect": 6,
          "characters": 1,
          "developer": 1,
          "has part": 1,
          "headquarters location": 1,
          "instrument": 1,
          "licensed to broadcast to": 14,
          "manufacturer": 2,
          "occupant": 1,
          "original network": 1,
          "owned by": 2,
          "screenwriter": 1,
          "subsidiary": 1
        },
        {
          "after a work by": 8,
          "applies to jurisdiction": 1,
          "architect": 1,
          "characters": 11,
          "composer": 10,
          "country of origin": 2,
          "developer": 4,
          "director": 8,
          "distributor": 4,
          "genre": 1,
          "has part": 5,
          "language of work or name": 1,
          "licensed to broadcast to": 1,
          "located in the administrative territorial entity": 1,
          "nominated for": 1,
          "notable work": 4,
          "occupant": 1,
          "original network": 12,
          "participating team": 1,
          "performer": 4,
          "platform": 1,
          "publisher": 1,
          "screenwriter": 6,
          "sports season of league or competition": 1
        },
        {
          "after a work by": 10,
          "characters": 5,
          "composer": 8,
          "country of origin": 7,
          "director": 14,
          "distributor": 4,
          "followed by": 3,
          "genre": 1,
          "headquarters location": 1,
          "language of work or name": 4,
          "licensed to broadcast to": 1,
          "location": 1,
          "location of formation": 1,
          "nominated for": 2,
          "notable work": 5,
          "original network": 2,
          "performer": 11,
          "screenwriter": 10
        },
        {
          "after a work by": 2,
          "applies to jurisdiction": 1,
          "architect": 1,
          "country of origin": 3,
          "distributor": 5,
          "followed by": 1,
          "has part": 1,
          "head of government": 1,
          "instance of": 1,
          "location": 12,
          "movement": 1,
          "nominated for": 4,
          "occupant": 2,
          "original network": 3,
          "owned by": 1,
          "participant": 16,
          "participant of": 6,
          "participating team": 5,
          "performer": 2,
          "publisher": 1,
          "screenwriter": 2,
          "sports season of league or competition": 8,
          "subsidiary": 1,
          "successful candidate": 1,
          "winner": 9
        },
        {
          "applies to jurisdiction": 1,
          "contains administrative territorial entity": 3,
          "country": 7,
          "country of origin": 2,
          "head of government": 1,
          "headquarters location": 3,
          "licensed to broadcast to": 33,
          "located in the administrative territorial entity": 8,
          "located on terrain feature": 1,
          "location": 2,
          "location of formation": 7,
          "manufacturer": 3,
          "military branch": 2,
          "operator": 4,
          "owned by": 2,
          "place served by transport hub": 3,
          "residence": 5,
          "subsidiary": 1,
          "work location": 1
        },
        {
          "characters": 1,
          "composer": 1,
          "contains administrative territorial entity": 1,
          "country of citizenship": 5,
          "father": 1,
          "head of government": 3,
          "instrument": 1,
          "location": 1,
          "member of political party": 24,
          "military branch": 7,
          "owned by": 1,
          "performer": 1,
          "position held": 7,
          "religion": 3,
          "residence": 12,
          "said to be the same as": 1,
          "sibling": 1,
          "successful candidate": 1,
          "work location": 8
        },
        {
          "applies to jurisdiction": 1,
          "architect": 1,
          "country": 2,
          "followed by": 1,
          "has part": 1,
          "headquarters location": 9,
          "league": 49,
          "licensed to broadcast to": 2,
          "located in the administrative territorial entity": 1,
          "location": 1,
          "location of formation": 3,
          "military branch": 2,
          "occupant": 9,
          "operator": 1,
          "owned by": 1,
          "participant of": 2,
          "participating team": 8,
          "religion": 1,
          "sports season of league or competition": 1,
          "subsidiary": 2,
          "winner": 1,
          "work location": 1
        },
        {
          "country of origin": 1,
          "headquarters location": 1,
          "original network": 1,
          "participant": 12,
          "participant of": 4,
          "performer": 2,
          "winner": 1
        },
        {
          "architect": 1,
          "contains administrative territorial entity": 2,
          "country": 3,
          "followed by": 1,
          "has part": 3,
          "heritage designation": 1,
          "instance of": 4,
          "located in the administrative territorial entity": 2,
          "located on terrain feature": 15,
          "mountain range": 15,
          "mouth of the watercourse": 26,
          "operator": 1,
          "owned by": 1,
          "place served by transport hub": 4,
          "said to be the same as": 1,
          "tributary": 13
        },
        {
          "contains administrative territorial entity": 4,
          "country": 8,
          "instance of": 2,
          "located in the administrative territorial entity": 9,
          "located on terrain feature": 19,
          "location": 1,
          "mountain range": 34,
          "mouth of the watercourse": 22,
          "said to be the same as": 1,
          "tributary": 10
        },
        {
          "country": 4,
          "has part": 5,
          "instance of": 2,
          "licensed to broadcast to": 2,
          "located in the administrative territorial entity": 3,
          "located on terrain feature": 5,
          "location": 1,
          "manufacturer": 1,
          "mountain range": 3,
          "operator": 1,
          "owned by": 2,
          "place served by transport hub": 29
        },
        {
          "applies to jurisdiction": 2,
          "contains administrative territorial entity": 47,
          "country": 15,
          "has part": 4,
          "instance of": 13,
          "located in the administrative territorial entity": 24,
          "located on terrain feature": 17,
          "location": 2,
          "mouth of the watercourse": 1
        },
        {
          "characters": 1,
          "country": 3,
          "country of origin": 1,
          "has part": 1,
          "headquarters location": 6,
          "instrument": 1,
          "league": 6,
          "licensed to broadcast to": 4,
          "located in the administrative territorial entity": 2,
          "located on terrain feature": 2,
          "location": 3,
          "location of formation": 3,
          "manufacturer": 4,
          "military branch": 1,
          "mountain range": 1,
          "occupant": 16,
          "operator": 2,
          "owned by": 2,
          "participant": 1,
          "place served by transport hub": 6,
          "residence": 1,
          "sports season of league or competition": 1
        },
        {
          "architect": 6,
          "contains administrative territorial entity": 1,
          "has part": 2,
          "headquarters location": 2,
          "instance of": 1,
          "league": 2,
          "located on terrain feature": 2,
          "location": 1,
          "manufacturer": 7,
          "military branch": 1,
          "occupant": 11,
          "operator": 10,
          "owned by": 3,
          "participant": 3,
          "participating team": 3,
          "place served by transport hub": 3,
          "sports season of league or competition": 1,
          "successful candidate": 1,
          "winner": 1
        },
        {
          "applies to jurisdiction": 1,
          "contains administrative territorial entity": 1,
          "followed by": 1,
          "has part": 2,
          "instance of": 1,
          "located on terrain feature": 5,
          "mountain range": 4,
          "mouth of the watercourse": 29,
          "said to be the same as": 2,
          "tributary": 35
        },
        {
          "applies to jurisdiction": 10,
          "characters": 1,
          "contains administrative territorial entity": 2,
          "country": 1,
          "director": 1,
          "followed by": 1,
          "has part": 2,
          "headquarters location": 12,
          "instance of": 1,
          "league": 6,
          "licensed to broadcast to": 1,
          "located in the administrative territorial entity": 3,
          "located on terrain feature": 1,
          "location": 1,
          "location of formation": 1,
          "manufacturer": 3,
          "military branch": 3,
          "occupant": 14,
          "operator": 13,
          "owned by": 7,
          "place served by transport hub": 7,
          "religion": 3,
          "subsidiary": 8
        },
        {
          "characters": 6,
          "contains administrative territorial entity": 2,
          "father": 5,
          "followed by": 1,
          "head of government": 1,
          "instance of": 1,
          "movement": 1,
          "occupation": 1,
          "position held": 1,
          "religion": 4,
          "said to be the same as": 9,
          "sibling": 5,
          "tributary": 1
        },
        {
          "applies to jurisdiction": 5,
          "country": 1,
          "country of origin": 1,
          "followed by": 1,
          "has part": 1,
          "head of government": 2,
          "location": 9,
          "military branch": 1,
          "participant": 21,
          "participating team": 1,
          "sports season of league or competition": 5,
          "successful candidate": 62,
          "winner": 1
        },
        {
          "country": 2,
          "country of citizenship": 3,
          "has part": 1,
          "headquarters location": 1,
          "league": 1,
          "located in the administrative territorial entity": 1,
          "location": 4,
          "occupant": 6,
          "owned by": 1,
          "participant": 6,
          "participant of": 11,
          "participating team": 34,
          "sports season of league or competition": 6,
          "winner": 25
        },
        {
          "country": 1,
          "country of origin": 1,
          "followed by": 24,
          "instance of": 2,
          "location": 1,
          "participant": 1,
          "participant of": 3,
          "participating team": 7,
          "sports season of league or competition": 27,
          "successful candidate": 3,
          "winner": 6
        },
        {
          "country of citizenship": 2,
          "director": 1,
          "instrument": 13,
          "nominated for": 6,
          "notable work": 3,
          "participant of": 1,
          "subsidiary": 1
        },
        {
          "developer": 1,
          "headquarters location": 1,
          "licensed to broadcast to": 4,
          "manufacturer": 2,
          "operator": 2,
          "owned by": 3,
          "subsidiary": 9
        },
        {
          "developer": 1,
          "distributor": 1,
          "genre": 6,
          "instance of": 1,
          "location": 1,
          "owned by": 1
        },
        {
          "applies to jurisdiction": 1,
          "country of citizenship": 1,
          "occupation": 1,
          "position held": 1,
          "successful candidate": 1
        },
        {
          "heritage designation": 73,
          "located in the administrative territorial entity": 1
        },
        {
          "country of origin": 1,
          "instance of": 1,
          "language of work or name": 9,
          "said to be the same as": 38,
          "taxon rank": 1
        },
        {
          "country of citizenship": 1,
          "followed by": 2,
          "instance of": 1,
          "military branch": 1,
          "said to be the same as": 1,
          "taxon rank": 22
        },
        {
          "instance of": 1,
          "taxon rank": 41
        },
        {
          "operator": 1
        },
        {
          "taxon rank": 7
        }
      ]
    ],
    "evaluation_time": 1.37,
    "v_measure": 0.46377246120542126,
    "v_measure_std": 0.0
  }
}