{
  "dataset_revision": null,
  "mteb_dataset_name": "RateMyProfClustering",
  "mteb_version": "1.1.2.dev0",
  "test": {
    "cluster_components": [
      [
        {
          "1) the professor's grading policies, test difficulty, or assessment-related issues": 69,
          "2) the amount of work, readings, or assignments required for the course as well as students' time investment": 78,
          "4) provides an opinion on the ease or difficulty of the course or its content": 107,
          "5) highlights the professor's demeanor, attitude, or personal qualities": 153
        },
        {
          "1) the professor's grading policies, test difficulty, or assessment-related issues": 152,
          "2) the amount of work, readings, or assignments required for the course as well as students' time investment": 160,
          "4) provides an opinion on the ease or difficulty of the course or its content": 88,
          "5) highlights the professor's demeanor, attitude, or personal qualities": 97
        },
        {
          "1) the professor's grading policies, test difficulty, or assessment-related issues": 166,
          "2) the amount of work, readings, or assignments required for the course as well as students' time investment": 154,
          "4) provides an opinion on the ease or difficulty of the course or its content": 218,
          "5) highlights the professor's demeanor, attitude, or personal qualities": 182
        },
        {
          "1) the professor's grading policies, test difficulty, or assessment-related issues": 187,
          "2) the amount of work, readings, or assignments required for the course as well as students' time investment": 182,
          "4) provides an opinion on the ease or difficulty of the course or its content": 161,
          "5) highlights the professor's demeanor, attitude, or personal qualities": 142
        }
      ]
    ],
    "evaluation_time": 0.13,
    "v_measure": 0.014954173581487092,
    "v_measure_std": 0.0
  }
}