{
  "dataset_revision": null,
  "mteb_dataset_name": "FeedbacksClustering",
  "mteb_version": "1.1.2.dev0",
  "test": {
    "cluster_components": [
      [
        {
          "1) Inclusion of Main Points and Necessary Details": 70,
          "2) Content Accuracy": 69,
          "3) Structure, Coherence or Grammatical Errors": 136
        },
        {
          "1) Inclusion of Main Points and Necessary Details": 141,
          "2) Content Accuracy": 103,
          "3) Structure, Coherence or Grammatical Errors": 96
        },
        {
          "1) Inclusion of Main Points and Necessary Details": 41,
          "2) Content Accuracy": 80,
          "3) Structure, Coherence or Grammatical Errors": 20
        }
      ]
    ],
    "evaluation_time": 0.09,
    "v_measure": 0.049537592125703744,
    "v_measure_std": 0.0
  }
}