{
  "dataset_revision": null,
  "mteb_dataset_name": "FeedbacksClustering",
  "mteb_version": "1.1.2.dev0",
  "test": {
    "cluster_components": [
      [
        {
          "1) Inclusion of Main Points and Necessary Details": 19,
          "2) Content Accuracy": 10,
          "3) Structure, Coherence or Grammatical Errors": 115
        },
        {
          "1) Inclusion of Main Points and Necessary Details": 159,
          "2) Content Accuracy": 198,
          "3) Structure, Coherence or Grammatical Errors": 28
        },
        {
          "1) Inclusion of Main Points and Necessary Details": 74,
          "2) Content Accuracy": 44,
          "3) Structure, Coherence or Grammatical Errors": 109
        }
      ]
    ],
    "evaluation_time": 0.06,
    "v_measure": 0.19818478331965733,
    "v_measure_std": 0.0
  }
}